[
  {
    "id": 4894928402649061,
    "created_at": "15分钟前",
    "source": "来自云南",
    "user": {
      "id": 7409934209,
      "screen_name": "一毛栗子呀",
      "profile_image_url": "https://tvax4.sinaimg.cn/crop.0.0.960.960.180/0085tknTly8h0ifejh00uj30qo0qoq5m.jpg?KID=imgbed,tva&Expires=1682537084&ssig=XtY%2FKwZIGc",
      "verified": false,
      "verified_type": -1,
      "followers_count": "5",
      "followers_count_str": "5",
      "friends_count": 90,
      "mbtype": 0,
      "svip": 0,
      "profile_url": "https://m.weibo.cn/u/7409934209?uid=7409934209",
      "remark": "",
      "following": false,
      "follow_me": false
    },
    "text": "好好背单词吧在接下来的日子<span class=\"url-icon\"><img alt=[抱抱] src=\"https://h5.sinaimg.cn/m/emoticon/icon/default/d_baobao-820d2c9a0f.png\" style=\"width:1em; height:1em;\" /></span>",
    "like_counts": 0,
    "liked": false,
    "recordTime": "2023-04-27 凌晨 12:09 星期四"
  },
  {
    "id": 4894928456389663,
    "created_at": "15分钟前",
    "source": "来自江苏",
    "user": {
      "id": 7813760968,
      "screen_name": "Lowkeyy_",
      "profile_image_url": "https://tvax1.sinaimg.cn/crop.0.0.793.793.180/008wNKaIly8hbxjfm7uh1j30m10m1t9x.jpg?KID=imgbed,tva&Expires=1682537084&ssig=aodmqgOSPd",
      "verified": false,
      "verified_type": -1,
      "followers_count": "2",
      "followers_count_str": "2",
      "friends_count": 57,
      "mbtype": 0,
      "svip": 0,
      "profile_url": "https://m.weibo.cn/u/7813760968?uid=7813760968",
      "remark": "",
      "following": false,
      "follow_me": false
    },
    "text": "嗨害 今年五一去看海咯 好久没去海边了。",
    "like_counts": 0,
    "liked": false,
    "recordTime": "2023-04-27 凌晨 12:09 星期四"
  },
  {
    "id": 4894929074262386,
    "created_at": "13分钟前",
    "source": "来自四川",
    "user": {
      "id": 3822691256,
      "screen_name": "每天都是神经病啊",
      "profile_image_url": "https://tvax2.sinaimg.cn/crop.0.0.1080.1080.180/e3d9a3b8ly8gexno0gzf1j20u00u0dir.jpg?KID=imgbed,tva&Expires=1682537084&ssig=8Pz838jiDZ",
      "verified": false,
      "verified_type": -1,
      "followers_count": "13",
      "followers_count_str": "13",
      "friends_count": 28,
      "mbtype": 0,
      "svip": 0,
      "profile_url": "https://m.weibo.cn/u/3822691256?uid=3822691256",
      "remark": "",
      "following": false,
      "follow_me": false
    },
    "text": "回复<a href='https://m.weibo.cn/n/夕花落雨'>@夕花落雨</a>:可是真的好累，每次都在内耗自己",
    "reply_id": 4894926112820241,
    "reply_text": "回复<a href='https://m.weibo.cn/n/每天都是神经病啊'>@每天都是神经病啊</a>:大家都一样，但也都在努力，一起加油吧唧",
    "like_counts": 0,
    "liked": false,
    "recordTime": "2023-04-27 凌晨 12:11 星期四"
  },
  {
    "id": 4894929715724440,
    "created_at": "10分钟前",
    "source": "来自安徽",
    "user": {
      "id": 7818975001,
      "screen_name": "卷卷同学在这里",
      "profile_image_url": "https://tvax3.sinaimg.cn/crop.0.0.940.940.180/008x9CA1ly8hanyph0qzsj30q40q4gn1.jpg?KID=imgbed,tva&Expires=1682537084&ssig=3b9mLBU4wg",
      "verified": false,
      "verified_type": -1,
      "followers_count": "0",
      "followers_count_str": "0",
      "friends_count": 24,
      "mbtype": 0,
      "svip": 0,
      "profile_url": "https://m.weibo.cn/u/7818975001?uid=7818975001",
      "remark": "",
      "following": false,
      "follow_me": false
    },
    "text": "晚安",
    "like_counts": 0,
    "liked": false,
    "recordTime": "2023-04-27 凌晨 12:14 星期四"
  },
  {
    "id": 4894929724116537,
    "created_at": "10分钟前",
    "source": "来自河南",
    "user": {
      "id": 5995089567,
      "screen_name": "心魔w",
      "profile_image_url": "https://tvax3.sinaimg.cn/crop.0.0.888.888.180/006xIMF1ly8h1s6zy2fnoj30oo0oodlw.jpg?KID=imgbed,tva&Expires=1682537084&ssig=VFJLCBl0DE",
      "verified": false,
      "verified_type": -1,
      "followers_count": "48",
      "followers_count_str": "48",
      "friends_count": 15,
      "mbtype": 2,
      "svip": 0,
      "profile_url": "https://m.weibo.cn/u/5995089567?uid=5995089567",
      "remark": "",
      "following": false,
      "follow_me": false
    },
    "text": "晚安",
    "like_counts": 0,
    "liked": false,
    "recordTime": "2023-04-27 凌晨 12:14 星期四"
  },
  {
    "id": 4894929996480574,
    "created_at": "9分钟前",
    "source": "来自山西",
    "user": {
      "id": 5175003262,
      "screen_name": "是你的冀先生啊",
      "profile_image_url": "https://tvax3.sinaimg.cn/crop.0.0.1080.1080.180/005EdMKyly8h5t8qtlnvqj30u00u0whw.jpg?KID=imgbed,tva&Expires=1682537084&ssig=toJBXHl43%2F",
      "verified": false,
      "verified_type": -1,
      "followers_count": "258",
      "followers_count_str": "258",
      "friends_count": 80,
      "mbtype": 2,
      "svip": 0,
      "profile_url": "https://m.weibo.cn/u/5175003262?uid=5175003262",
      "remark": "",
      "following": false,
      "follow_me": false
    },
    "text": "回复<a href='https://m.weibo.cn/n/神仙湾去吃沙子不'>@神仙湾去吃沙子不</a>:谢谢",
    "reply_id": 4894437819285886,
    "reply_text": "回复<a href='https://m.weibo.cn/n/是你的冀先生啊'>@是你的冀先生啊</a>:白头偕老，早生贵子。",
    "like_counts": 0,
    "liked": false,
    "recordTime": "2023-04-27 凌晨 12:15 星期四"
  },
  {
    "id": 4894930164519543,
    "created_at": "8分钟前",
    "source": "来自上海",
    "user": {
      "id": 1737523100,
      "screen_name": "耍小脾气的蚊子",
      "profile_image_url": "https://tva2.sinaimg.cn/crop.0.0.180.180.180/67907f9cjw1e8qgp5bmzyj2050050aa8.jpg?KID=imgbed,tva&Expires=1682537084&ssig=MDIADfH901",
      "verified": false,
      "verified_type": 220,
      "followers_count": "557",
      "followers_count_str": "557",
      "friends_count": 507,
      "mbtype": 12,
      "svip": 0,
      "profile_url": "https://m.weibo.cn/u/1737523100?uid=1737523100",
      "remark": "",
      "following": false,
      "follow_me": false
    },
    "text": "hi，我又来找您聊天了～～时隔两年半明天又要再次出发了，没有激动，没有无助，这次带上孩子一起。希望小人儿咳嗽快点好，也希望这从一切顺利。本月29号开始就不需要看核酸回国了，这是多少人的付出与牺牲换来今天，感恩！",
    "like_counts": 1,
    "liked": false,
    "recordTime": "2023-04-27 凌晨 12:16 星期四"
  },
  {
    "id": 4894931838308543,
    "created_at": "2分钟前",
    "source": "来自四川",
    "user": {
      "id": 7266304316,
      "screen_name": "称头里细娃",
      "profile_image_url": "https://tvax4.sinaimg.cn/crop.0.0.664.664.180/007VKFGIly8g61pi56lfyj30ig0iggmj.jpg?KID=imgbed,tva&Expires=1682537084&ssig=ztTzIsNLYG",
      "verified": false,
      "verified_type": -1,
      "followers_count": "40",
      "followers_count_str": "40",
      "friends_count": 538,
      "mbtype": 2,
      "svip": 0,
      "profile_url": "https://m.weibo.cn/u/7266304316?uid=7266304316",
      "remark": "",
      "following": false,
      "follow_me": false
    },
    "text": "李医生，一切会好的对吧！",
    "like_counts": 0,
    "liked": false,
    "recordTime": "2023-04-27 凌晨 12:22 星期四"
  },
  {
    "id": 4894933632944492,
    "created_at": "8分钟前",
    "source": "来自湖南",
    "user": {
      "id": 6296516238,
      "screen_name": "一百斤小龙虾",
      "profile_image_url": "https://tvax2.sinaimg.cn/crop.0.0.1080.1080.180/006S7xvwly8haqqj8b17pj30u00u0dhw.jpg?KID=imgbed,tva&Expires=1682537915&ssig=Fv7qiiDcnJ",
      "verified": false,
      "verified_type": -1,
      "followers_count": "17",
      "followers_count_str": "17",
      "friends_count": 121,
      "mbtype": 0,
      "svip": 0,
      "profile_url": "https://m.weibo.cn/u/6296516238?uid=6296516238",
      "remark": "",
      "following": false,
      "follow_me": false
    },
    "text": "一切都会好的！",
    "like_counts": 0,
    "liked": false,
    "recordTime": "2023-04-27 凌晨 12:30 星期四"
  },
  {
    "id": 4894933959574560,
    "created_at": "7分钟前",
    "source": "来自天津",
    "user": {
      "id": 7412142839,
      "screen_name": "温柔似水争朝夕",
      "profile_image_url": "https://tvax4.sinaimg.cn/crop.0.0.996.996.180/0085CAWXly8h10djtperfj30ro0rogog.jpg?KID=imgbed,tva&Expires=1682537915&ssig=3kgnEv%2Fd%2F4",
      "verified": false,
      "verified_type": -1,
      "followers_count": "18",
      "followers_count_str": "18",
      "friends_count": 462,
      "mbtype": 0,
      "svip": 0,
      "profile_url": "https://m.weibo.cn/u/7412142839?uid=7412142839",
      "remark": "",
      "following": false,
      "follow_me": false
    },
    "text": "会好的都会好的<span class=\"url-icon\"><img alt=\"[送花花]\" src=\"https://face.t.sinajs.cn/t4/appstyle/expression/ext/normal/cb/2022_Flowers_org.png\" style=\"width:1em; height:1em;\" /></span><span class=\"url-icon\"><img alt=\"[送花花]\" src=\"https://face.t.sinajs.cn/t4/appstyle/expression/ext/normal/cb/2022_Flowers_org.png\" style=\"width:1em; height:1em;\" /></span><span class=\"url-icon\"><img alt=\"[送花花]\" src=\"https://face.t.sinajs.cn/t4/appstyle/expression/ext/normal/cb/2022_Flowers_org.png\" style=\"width:1em; height:1em;\" /></span>当然会好的",
    "like_counts": 0,
    "liked": false,
    "recordTime": "2023-04-27 凌晨 12:31 星期四"
  },
  {
    "id": 4894934051586397,
    "created_at": "7分钟前",
    "source": "来自天津",
    "user": {
      "id": 7412142839,
      "screen_name": "温柔似水争朝夕",
      "profile_image_url": "https://tvax4.sinaimg.cn/crop.0.0.996.996.180/0085CAWXly8h10djtperfj30ro0rogog.jpg?KID=imgbed,tva&Expires=1682537915&ssig=3kgnEv%2Fd%2F4",
      "verified": false,
      "verified_type": -1,
      "followers_count": "18",
      "followers_count_str": "18",
      "friends_count": 462,
      "mbtype": 0,
      "svip": 0,
      "profile_url": "https://m.weibo.cn/u/7412142839?uid=7412142839",
      "remark": "",
      "following": false,
      "follow_me": false
    },
    "text": "勇敢坚强温柔善良积极向上<span class=\"url-icon\"><img alt=\"[锦鲤附体]\" src=\"https://face.t.sinajs.cn/t4/appstyle/expression/ext/normal/30/2022_Koi_org.png\" style=\"width:1em; height:1em;\" /></span><span class=\"url-icon\"><img alt=\"[锦鲤附体]\" src=\"https://face.t.sinajs.cn/t4/appstyle/expression/ext/normal/30/2022_Koi_org.png\" style=\"width:1em; height:1em;\" /></span><span class=\"url-icon\"><img alt=\"[锦鲤附体]\" src=\"https://face.t.sinajs.cn/t4/appstyle/expression/ext/normal/30/2022_Koi_org.png\" style=\"width:1em; height:1em;\" /></span>",
    "like_counts": 0,
    "liked": false,
    "recordTime": "2023-04-27 凌晨 12:31 星期四"
  },
  {
    "id": 4894934845624215,
    "created_at": "4分钟前",
    "source": "来自广东",
    "user": {
      "id": 7684990743,
      "screen_name": "moonchild-yg",
      "profile_image_url": "https://tvax4.sinaimg.cn/crop.0.0.664.664.180/008o5r9Bly8gty4qgtd2pj60ig0igabh02.jpg?KID=imgbed,tva&Expires=1682537915&ssig=%2FsmxxlMR4s",
      "verified": false,
      "verified_type": -1,
      "followers_count": "0",
      "followers_count_str": "0",
      "friends_count": 184,
      "mbtype": 0,
      "svip": 0,
      "profile_url": "https://m.weibo.cn/u/7684990743?uid=7684990743",
      "remark": "",
      "following": false,
      "follow_me": false
    },
    "text": "回复<a href='https://m.weibo.cn/n/每天都是神经病啊'>@每天都是神经病啊</a>:我们先歇一下脚吧，今天已经努力了，所以可以早点睡",
    "reply_id": 4894924980355591,
    "reply_text": "我好累  能不能有个地方一个人 没有经济压力 一个人过日子",
    "like_counts": 0,
    "liked": false,
    "recordTime": "2023-04-27 凌晨 12:34 星期四"
  },
  {
    "id": 4894934908274996,
    "created_at": "3分钟前",
    "source": "来自浙江",
    "user": {
      "id": 3152275022,
      "screen_name": "三花冬青呀",
      "profile_image_url": "https://tvax4.sinaimg.cn/crop.0.0.719.719.180/bbe3e64ely8hafxpda7adj20jz0jzq3w.jpg?KID=imgbed,tva&Expires=1682537915&ssig=ztz0Z%2Bmupz",
      "verified": false,
      "verified_type": -1,
      "followers_count": "231",
      "followers_count_str": "231",
      "friends_count": 67,
      "mbtype": 0,
      "svip": 0,
      "profile_url": "https://m.weibo.cn/u/3152275022?uid=3152275022",
      "remark": "",
      "following": false,
      "follow_me": false
    },
    "text": "夜深了",
    "like_counts": 0,
    "liked": false,
    "recordTime": "2023-04-27 凌晨 12:35 星期四"
  },
  {
    "id": 4894934950216157,
    "created_at": "3分钟前",
    "source": "来自浙江",
    "user": {
      "id": 3152275022,
      "screen_name": "三花冬青呀",
      "profile_image_url": "https://tvax4.sinaimg.cn/crop.0.0.719.719.180/bbe3e64ely8hafxpda7adj20jz0jzq3w.jpg?KID=imgbed,tva&Expires=1682537915&ssig=ztz0Z%2Bmupz",
      "verified": false,
      "verified_type": -1,
      "followers_count": "231",
      "followers_count_str": "231",
      "friends_count": 67,
      "mbtype": 0,
      "svip": 0,
      "profile_url": "https://m.weibo.cn/u/3152275022?uid=3152275022",
      "remark": "",
      "following": false,
      "follow_me": false
    },
    "text": "你为什么还不睡",
    "like_counts": 0,
    "liked": false,
    "recordTime": "2023-04-27 凌晨 12:35 星期四"
  }
]
