[
  {
    "id": 4936604189987305,
    "created_at": "刚刚",
    "source": "来自贵州",
    "user": {
      "id": 3592575063,
      "screen_name": "黑衣红玫瑰",
      "profile_image_url": "https://tvax4.sinaimg.cn/crop.0.0.1002.1002.180/d6225857ly8gxzg6u8dl2j20ru0ru76r.jpg?KID=imgbed,tva&Expires=1692472426&ssig=k2iznp7EcM",
      "verified": false,
      "verified_type": -1,
      "followers_count": "460",
      "followers_count_str": "460",
      "friends_count": 439,
      "mbtype": 2,
      "svip": 0,
      "profile_url": "https://m.weibo.cn/u/3592575063?",
      "remark": "",
      "following": false,
      "follow_me": false
    },
    "text": "今天绕两个城区走了15公里，两瓶矿泉水一瓶蓝色尖叫。<span class=\"url-icon\"><img alt=[太开心] src=\"https://h5.sinaimg.cn/m/emoticon/icon/default/d_taikaixin-b7d86de3fd.png\" style=\"width:1em; height:1em;\" /></span>",
    "like_counts": 0,
    "liked": false,
    "recordTime": "2023-08-20 凌晨 12:13 星期日"
  },
  {
    "id": 4936604035319851,
    "created_at": "刚刚",
    "source": "来自广东",
    "user": {
      "id": 1715286261,
      "screen_name": "居Lee夫人",
      "profile_image_url": "https://tvax4.sinaimg.cn/crop.0.0.1044.1044.180/663d30f5ly8h4oc8j6ai9j20t00t0jur.jpg?KID=imgbed,tva&Expires=1692472426&ssig=%2F1b2n%2FHnit",
      "verified": false,
      "verified_type": -1,
      "followers_count": "1302",
      "followers_count_str": "1302",
      "friends_count": 457,
      "mbtype": 2,
      "svip": 0,
      "profile_url": "https://m.weibo.cn/u/1715286261?",
      "remark": "",
      "following": false,
      "follow_me": false
    },
    "text": "回复<a href='https://m.weibo.cn/n/居Lee夫人'>@居Lee夫人</a>:“有因必有果，等着吧！”这是一个母亲对女儿的诅咒吗？真的是瞬间刷新我三十多年的认知，为什么，这个世界上还有谁可以相信，还有谁真心希望你好吗？母亲都可以说这样点话，可能真的不可能再有吧",
    "reply_id": 4936602021792403,
    "reply_text": "你对我就没有伤害过吗！！疫情那年生日我和女儿过生日好不容易买到一个蛋糕我们在家唱生日歌吹蜡烛，你为什么板个脸坐在旁边没有任何反应！为什么要这样！你有什么不满意你可以说出来！为什么要这么恶心人！！为什么！！<span class=\"url-icon\"><img alt=[泪] src=\"https://h5.sinaimg.cn/m/emoticon/icon/default/d_lei-4cdf6ee412.png\" style=\"width:1em; height:1em;\" /></span>",
    "like_counts": 0,
    "liked": false,
    "recordTime": "2023-08-20 凌晨 12:13 星期日"
  },
  {
    "id": 4936603875151548,
    "created_at": "1分钟前",
    "source": "来自安徽",
    "user": {
      "id": 7676887296,
      "screen_name": "礼拜天zz",
      "profile_image_url": "https://tvax3.sinaimg.cn/crop.0.0.828.828.180/008nxr4Qly8guoqevo7f9j60n00n03zx02.jpg?KID=imgbed,tva&Expires=1692472426&ssig=O9LLaLnREM",
      "verified": false,
      "verified_type": -1,
      "followers_count": "0",
      "followers_count_str": "0",
      "friends_count": 14,
      "mbtype": 0,
      "svip": 0,
      "profile_url": "https://m.weibo.cn/u/7676887296?",
      "remark": "",
      "following": false,
      "follow_me": false
    },
    "text": "嘿嘿愉快的周末",
    "like_counts": 0,
    "liked": false,
    "recordTime": "2023-08-20 凌晨 12:12 星期日"
  },
  {
    "id": 4936603456504525,
    "created_at": "3分钟前",
    "source": "来自广东",
    "user": {
      "id": 5710482421,
      "screen_name": "刘炬庚",
      "profile_image_url": "https://tvax4.sinaimg.cn/crop.0.0.512.512.180/006esBlbly8h0drblsbdtj30e80e874z.jpg?KID=imgbed,tva&Expires=1692472426&ssig=emCTI%2FLwCR",
      "verified": false,
      "verified_type": -1,
      "followers_count": "69",
      "followers_count_str": "69",
      "friends_count": 92,
      "mbtype": 2,
      "svip": 0,
      "profile_url": "https://m.weibo.cn/u/5710482421?",
      "remark": "",
      "following": false,
      "follow_me": false
    },
    "text": "疫情结束了 我又和她重新开始了 李医生 晚安<span class=\"url-icon\"><img alt=[兔子] src=\"https://h5.sinaimg.cn/m/emoticon/icon/others/d_tuzi-d2b0222faa.png\" style=\"width:1em; height:1em;\" /></span>",
    "like_counts": 0,
    "liked": false,
    "recordTime": "2023-08-20 凌晨 12:10 星期日"
  },
  {
    "id": 4936602277906424,
    "created_at": "7分钟前",
    "source": "来自黑龙江",
    "user": {
      "id": 6345031935,
      "screen_name": "土豆是食物的王",
      "profile_image_url": "https://tvax1.sinaimg.cn/crop.0.0.1080.1080.180/006Vp6ELly8hgxu0uv9uoj30u00u0mzt.jpg?KID=imgbed,tva&Expires=1692472426&ssig=mLwoRtU9O7",
      "verified": false,
      "verified_type": -1,
      "followers_count": "10",
      "followers_count_str": "10",
      "friends_count": 67,
      "mbtype": 0,
      "svip": 0,
      "profile_url": "https://m.weibo.cn/u/6345031935?",
      "remark": "",
      "following": false,
      "follow_me": false
    },
    "text": "睡觉喽",
    "like_counts": 0,
    "liked": false,
    "recordTime": "2023-08-20 凌晨 12:06 星期日"
  },
  {
    "id": 4936602021792403,
    "created_at": "8分钟前",
    "source": "来自广东",
    "user": {
      "id": 1715286261,
      "screen_name": "居Lee夫人",
      "profile_image_url": "https://tvax4.sinaimg.cn/crop.0.0.1044.1044.180/663d30f5ly8h4oc8j6ai9j20t00t0jur.jpg?KID=imgbed,tva&Expires=1692472426&ssig=%2F1b2n%2FHnit",
      "verified": false,
      "verified_type": -1,
      "followers_count": "1302",
      "followers_count_str": "1302",
      "friends_count": 457,
      "mbtype": 2,
      "svip": 0,
      "profile_url": "https://m.weibo.cn/u/1715286261?",
      "remark": "",
      "following": false,
      "follow_me": false
    },
    "text": "你对我就没有伤害过吗！！疫情那年生日我和女儿过生日好不容易买到一个蛋糕我们在家唱生日歌吹蜡烛，你为什么板个脸坐在旁边没有任何反应！为什么要这样！你有什么不满意你可以说出来！为什么要这么恶心人！！为什么！！<span class=\"url-icon\"><img alt=[泪] src=\"https://h5.sinaimg.cn/m/emoticon/icon/default/d_lei-4cdf6ee412.png\" style=\"width:1em; height:1em;\" /></span>",
    "like_counts": 0,
    "liked": false,
    "recordTime": "2023-08-20 凌晨 12:05 星期日"
  },
  {
    "id": 4936601920603501,
    "created_at": "9分钟前",
    "source": "来自山东",
    "user": {
      "id": 2041486451,
      "screen_name": "豆浆油条0703",
      "profile_image_url": "https://tvax1.sinaimg.cn/crop.0.0.996.996.180/79ae9c73ly8fqfmzqogusj20ro0rogo6.jpg?KID=imgbed,tva&Expires=1692472426&ssig=RAeHLgJJPL",
      "verified": false,
      "verified_type": 220,
      "followers_count": "1122",
      "followers_count_str": "1122",
      "friends_count": 534,
      "mbtype": 2,
      "svip": 0,
      "profile_url": "https://m.weibo.cn/u/2041486451?",
      "remark": "",
      "following": false,
      "follow_me": false
    },
    "text": "看微博时候，总会来看看你。",
    "like_counts": 0,
    "liked": false,
    "recordTime": "2023-08-20 凌晨 12:04 星期日"
  },
  {
    "id": 4936601458709762,
    "created_at": "10分钟前",
    "source": "来自浙江",
    "user": {
      "id": 5524056674,
      "screen_name": "三傻姑娘",
      "profile_image_url": "https://tvax4.sinaimg.cn/crop.0.0.996.996.180/0061Qnuily8gp11w7dp20j30ro0rpdj9.jpg?KID=imgbed,tva&Expires=1692472426&ssig=nxq%2F1xzXm%2B",
      "verified": false,
      "verified_type": -1,
      "followers_count": "63",
      "followers_count_str": "63",
      "friends_count": 207,
      "mbtype": 0,
      "svip": 0,
      "profile_url": "https://m.weibo.cn/u/5524056674?",
      "remark": "",
      "following": false,
      "follow_me": false
    },
    "text": "以前最害怕一个人去医院 现在可以一个人签字面对所有了 我们都会活的越来越勇敢的对吧",
    "like_counts": 0,
    "liked": false,
    "recordTime": "2023-08-20 凌晨 12:03 星期日"
  },
  {
    "id": 4936600356127090,
    "created_at": "15分钟前",
    "source": "来自浙江",
    "user": {
      "id": 6065998599,
      "screen_name": "阿里善的姑娘",
      "profile_image_url": "https://tvax4.sinaimg.cn/crop.0.0.470.470.180/006Cwjl5ly8hg9v3pp8nkj30d20d2aan.jpg?KID=imgbed,tva&Expires=1692472426&ssig=psjbTXcKwM",
      "verified": false,
      "verified_type": -1,
      "followers_count": "228",
      "followers_count_str": "228",
      "friends_count": 7,
      "mbtype": 2,
      "svip": 0,
      "profile_url": "https://m.weibo.cn/u/6065998599?",
      "remark": "",
      "following": false,
      "follow_me": false
    },
    "text": "回复<a href='https://m.weibo.cn/n/阿里善的姑娘'>@阿里善的姑娘</a>:生活中若能有这样的人相伴，真的是太幸运了。也就只有频率相同的人，才能看到彼此内心深处不为人知的优雅，懂你的言外之意，理解你的山河万里，尊重你的与众不同。",
    "reply_id": 4936600243669933,
    "reply_text": "有些人相处起来就特别舒服，既能聊搞笑，又能聊不正经。既能聊生活琐碎，也能谈工作宏图，在某些事情上也有独到见解，可以耐心的沟通，懂得分享，特别是能换位思考，真心待人，不至于严肃呆板或者太低级趣味。",
    "like_counts": 0,
    "liked": false,
    "recordTime": "2023-08-19 晚上 11:58 星期六"
  }
]
