[
  {
    "id": 4877899536007489,
    "created_at": "刚刚",
    "source": "来自贵州",
    "user": {
      "id": 7183586541,
      "screen_name": "谁嗦了我的螺狮粉",
      "profile_image_url": "https://tvax1.sinaimg.cn/crop.0.0.512.512.180/007Q9B13ly8h6p0ay9b3rj30e80e80te.jpg?KID=imgbed,tva&Expires=1678476195&ssig=k592qYPMri",
      "verified": false,
      "verified_type": -1,
      "followers_count": "2",
      "followers_count_str": "2",
      "friends_count": 156,
      "mbtype": 0,
      "svip": 0,
      "profile_url": "https://m.weibo.cn/u/7183586541?uid=7183586541",
      "remark": "",
      "following": false,
      "follow_me": false
    },
    "text": "李叔叔，晚安啦",
    "like_counts": 0,
    "liked": false,
    "recordTime": "2023-03-11 凌晨 12:23 星期六"
  },
  {
    "id": 4877897850947479,
    "created_at": "7分钟前",
    "source": "来自山东",
    "user": {
      "id": 6887027014,
      "screen_name": "卿相1白衣2",
      "profile_image_url": "https://tvax2.sinaimg.cn/crop.0.0.1000.1000.180/007w5gkSly8h0datu6iofj30rs0rs794.jpg?KID=imgbed,tva&Expires=1678476195&ssig=QtCD0MBzA1",
      "verified": false,
      "verified_type": -1,
      "followers_count": "4",
      "followers_count_str": "4",
      "friends_count": 353,
      "mbtype": 0,
      "svip": 0,
      "profile_url": "https://m.weibo.cn/u/6887027014?uid=6887027014",
      "remark": "",
      "following": false,
      "follow_me": false
    },
    "text": "晚安 李医生",
    "like_counts": 0,
    "liked": false,
    "recordTime": "2023-03-11 凌晨 12:16 星期六",
    "originTime": "2023-03-10T16:16:15.390Z"
  },
  {
    "id": 4877897754478700,
    "created_at": "8分钟前",
    "source": "来自河北",
    "user": {
      "id": 6152897028,
      "screen_name": "Mysnake7p",
      "profile_image_url": "https://tvax1.sinaimg.cn/crop.0.0.1076.1076.180/006IoVAEly8h8ieyvyp8fj30tw0tw76t.jpg?KID=imgbed,tva&Expires=1678476195&ssig=3iT8BsEZNc",
      "verified": false,
      "verified_type": -1,
      "followers_count": "109",
      "followers_count_str": "109",
      "friends_count": 129,
      "mbtype": 2,
      "svip": 0,
      "profile_url": "https://m.weibo.cn/u/6152897028?uid=6152897028",
      "remark": "",
      "following": false,
      "follow_me": false
    },
    "text": "失眠",
    "like_counts": 0,
    "liked": false,
    "recordTime": "2023-03-11 凌晨 12:15 星期六",
    "originTime": "2023-03-10T16:15:15.390Z"
  },
  {
    "id": 4877896344667825,
    "created_at": "13分钟前",
    "source": "来自山西",
    "user": {
      "id": 7728875181,
      "screen_name": "慢慢困住了",
      "profile_image_url": "https://tvax2.sinaimg.cn/crop.0.0.600.600.180/008r3zv7ly8hbs5rh7sbtj30go0got9l.jpg?KID=imgbed,tva&Expires=1678476195&ssig=VKPBSRHYke",
      "verified": false,
      "verified_type": -1,
      "followers_count": "105",
      "followers_count_str": "105",
      "friends_count": 80,
      "mbtype": 11,
      "svip": 0,
      "profile_url": "https://m.weibo.cn/u/7728875181?uid=7728875181",
      "remark": "",
      "following": false,
      "follow_me": false
    },
    "text": "晚安李医生",
    "like_counts": 1,
    "liked": false,
    "recordTime": "2023-03-11 凌晨 12:10 星期六",
    "originTime": "2023-03-10T16:10:15.390Z"
  },
  {
    "id": 4877895853411529,
    "created_at": "15分钟前",
    "source": "来自湖北",
    "user": {
      "id": 7809706218,
      "screen_name": "长舟821",
      "profile_image_url": "https://tvax3.sinaimg.cn/crop.0.0.1080.1080.180/008wwJlwly8h9d2vjls4mj30u00u0qa3.jpg?KID=imgbed,tva&Expires=1678476195&ssig=jJX45S1T4Y",
      "verified": false,
      "verified_type": -1,
      "followers_count": "0",
      "followers_count_str": "0",
      "friends_count": 11,
      "mbtype": 0,
      "svip": 0,
      "profile_url": "https://m.weibo.cn/u/7809706218?uid=7809706218",
      "remark": "",
      "following": false,
      "follow_me": false
    },
    "text": "晚安……",
    "like_counts": 0,
    "liked": false,
    "recordTime": "2023-03-11 凌晨 12:08 星期六",
    "originTime": "2023-03-10T16:08:15.391Z"
  },
  {
    "id": 4877895384432738,
    "created_at": "17分钟前",
    "source": "来自广东",
    "user": {
      "id": 2402312710,
      "screen_name": "林檬佰香果",
      "profile_image_url": "https://tvax3.sinaimg.cn/crop.0.0.996.996.180/8f306206ly8g9wk8rcwnjj20ro0rodhi.jpg?KID=imgbed,tva&Expires=1678476195&ssig=qFzchbUAYj",
      "verified": false,
      "verified_type": -1,
      "followers_count": "88",
      "followers_count_str": "88",
      "friends_count": 108,
      "mbtype": 0,
      "svip": 0,
      "profile_url": "https://m.weibo.cn/u/2402312710?uid=2402312710",
      "remark": "",
      "following": false,
      "follow_me": false
    },
    "text": "老李，好累啊，到现在还没找到工作，都不知道做什么，该怎么办<span class=\"url-icon\"><img alt=[泪] src=\"https://h5.sinaimg.cn/m/emoticon/icon/default/d_lei-4cdf6ee412.png\" style=\"width:1em; height:1em;\" /></span><span class=\"url-icon\"><img alt=[泪] src=\"https://h5.sinaimg.cn/m/emoticon/icon/default/d_lei-4cdf6ee412.png\" style=\"width:1em; height:1em;\" /></span><span class=\"url-icon\"><img alt=[泪] src=\"https://h5.sinaimg.cn/m/emoticon/icon/default/d_lei-4cdf6ee412.png\" style=\"width:1em; height:1em;\" /></span>",
    "like_counts": 0,
    "liked": false,
    "recordTime": "2023-03-11 凌晨 12:06 星期六",
    "originTime": "2023-03-10T16:06:15.391Z"
  },
  {
    "id": 4877895233700012,
    "created_at": "18分钟前",
    "source": "来自辽宁",
    "user": {
      "id": 6159818031,
      "screen_name": "海边的十三郎",
      "profile_image_url": "https://tvax1.sinaimg.cn/crop.0.0.900.900.180/006IRY3Jly8h91wyg4w4jj30p00p0jt4.jpg?KID=imgbed,tva&Expires=1678476195&ssig=onyGlwMEYN",
      "verified": false,
      "verified_type": -1,
      "followers_count": "19",
      "followers_count_str": "19",
      "friends_count": 194,
      "mbtype": 0,
      "svip": 0,
      "profile_url": "https://m.weibo.cn/u/6159818031?uid=6159818031",
      "remark": "",
      "following": false,
      "follow_me": false
    },
    "text": "今天我彩票中一等奖！",
    "like_counts": 0,
    "liked": false,
    "recordTime": "2023-03-11 凌晨 12:05 星期六",
    "originTime": "2023-03-10T16:05:15.391Z"
  },
  {
    "id": 4877894557893691,
    "created_at": "20分钟前",
    "source": "来自安徽",
    "user": {
      "id": 5027733486,
      "screen_name": "KiKi冉同学",
      "profile_image_url": "https://tva4.sinaimg.cn/crop.0.0.664.664.180/005ufR9Ajw8f922ak0zwbj30ig0igabb.jpg?KID=imgbed,tva&Expires=1678476195&ssig=PkDiG8reiY",
      "verified": false,
      "verified_type": -1,
      "followers_count": "130",
      "followers_count_str": "130",
      "friends_count": 284,
      "mbtype": 0,
      "svip": 0,
      "profile_url": "https://m.weibo.cn/u/5027733486?uid=5027733486",
      "remark": "",
      "following": false,
      "follow_me": false
    },
    "text": "只能说人生没有那么多如果，还是要现实一点，做好自己的事情，走好自己的路。",
    "like_counts": 0,
    "liked": false,
    "recordTime": "2023-03-11 凌晨 12:03 星期六",
    "originTime": "2023-03-10T16:03:15.391Z"
  },
  {
    "id": 4877894088130797,
    "created_at": "22分钟前",
    "source": "来自安徽",
    "user": {
      "id": 6335976484,
      "screen_name": "Liliy小妮呀",
      "profile_image_url": "https://tvax1.sinaimg.cn/crop.0.0.1080.1080.180/006UN6V6ly8ha4sxxkb62j30u00u0ju0.jpg?KID=imgbed,tva&Expires=1678476195&ssig=GEXmDtqOhM",
      "verified": false,
      "verified_type": -1,
      "followers_count": "114",
      "followers_count_str": "114",
      "friends_count": 263,
      "mbtype": 2,
      "svip": 0,
      "profile_url": "https://m.weibo.cn/u/6335976484?uid=6335976484",
      "remark": "",
      "following": false,
      "follow_me": false
    },
    "text": "他发烧了。我给他买了药 退烧的和抗病毒的 我耐心和他说 哪两种不能一起吃 哪一种隔几个小时就可以吃。很正常的一件小事。 他突然愣住 对我说:“我好想哭 你对我这么好。”我也愣住了 突然感觉他有时也很脆弱 像小男生 这是旁人都看不到的一面。我学着他平时哄我的样子 对他说:“乖。我在呢” 晚安",
    "like_counts": 1,
    "liked": false,
    "recordTime": "2023-03-11 凌晨 12:01 星期六",
    "originTime": "2023-03-10T16:01:15.391Z"
  }
]
