[
  {
    "id": 4903985238249656,
    "created_at": "18分钟前",
    "source": "来自湖北",
    "user": {
      "id": 6013063995,
      "screen_name": "yoyo言小言",
      "profile_image_url": "https://tvax3.sinaimg.cn/crop.0.0.1080.1080.180/006yWcD9ly8gdggyade8sj30u00u0acp.jpg?KID=imgbed,tva&Expires=1684696540&ssig=%2BervHeQwz5",
      "verified": false,
      "verified_type": -1,
      "followers_count": "510",
      "followers_count_str": "510",
      "friends_count": 87,
      "mbtype": 2,
      "svip": 0,
      "profile_url": "https://m.weibo.cn/u/6013063995?",
      "remark": "",
      "following": false,
      "follow_me": false
    },
    "text": "回复<a href='https://m.weibo.cn/n/卤蛋猫猫的胖布兜'>@卤蛋猫猫的胖布兜</a>:都不容易<span class=\"url-icon\"><img alt=[抱抱] src=\"https://h5.sinaimg.cn/m/emoticon/icon/default/d_baobao-820d2c9a0f.png\" style=\"width:1em; height:1em;\" /></span>",
    "reply_id": 4903979635442050,
    "reply_text": "回复<a href='https://m.weibo.cn/n/yoyo言小言'>@yoyo言小言</a>:<span class=\"url-icon\"><img alt=[抱抱] src=\"https://h5.sinaimg.cn/m/emoticon/icon/default/d_baobao-820d2c9a0f.png\" style=\"width:1em; height:1em;\" /></span><span class=\"url-icon\"><img alt=[抱抱] src=\"https://h5.sinaimg.cn/m/emoticon/icon/default/d_baobao-820d2c9a0f.png\" style=\"width:1em; height:1em;\" /></span>倒数的日子，至少强过一眼望到头的日子<span class=\"url-icon\"><img alt=[单身狗] src=\"https://h5.sinaimg.cn/m/emoticon/icon/_/co_niuec-7d05bc992a.png\" style=\"width:1em; height:1em;\" /></span>",
    "like_counts": 0,
    "liked": false,
    "recordTime": "2023-05-21 晚上 11:57 星期日"
  },
  {
    "id": 4903984785787955,
    "created_at": "19分钟前",
    "source": "来自山东",
    "user": {
      "id": 2989818954,
      "screen_name": "Latormenta2004",
      "profile_image_url": "https://tvax4.sinaimg.cn/crop.0.0.592.592.180/b235044aly8hcwtks2h0jj20gg0gg75f.jpg?KID=imgbed,tva&Expires=1684696540&ssig=sCCDXCJHRl",
      "verified": false,
      "verified_type": -1,
      "followers_count": "916",
      "followers_count_str": "916",
      "friends_count": 326,
      "mbtype": 12,
      "svip": 0,
      "profile_url": "https://m.weibo.cn/u/2989818954?",
      "remark": "",
      "following": false,
      "follow_me": false
    },
    "text": "越来越觉得自己是个很没用的人。。为什么别人都能做到的事对我来说就那么难呢？是不是我太矫情了",
    "like_counts": 0,
    "liked": false,
    "recordTime": "2023-05-21 晚上 11:56 星期日"
  },
  {
    "id": 4903984756165553,
    "created_at": "20分钟前",
    "source": "来自广东",
    "user": {
      "id": 7354698118,
      "screen_name": "三三两两淅淅沥沥",
      "profile_image_url": "https://tvax1.sinaimg.cn/default/images/default_avatar_female_180.gif?KID=imgbed,tva&Expires=1684696540&ssig=%2Bw9a5zi6nx",
      "verified": false,
      "verified_type": -1,
      "followers_count": "4",
      "followers_count_str": "4",
      "friends_count": 5,
      "mbtype": 0,
      "svip": 0,
      "profile_url": "https://m.weibo.cn/u/7354698118?",
      "remark": "",
      "following": false,
      "follow_me": false
    },
    "text": "李医生，我已经饱受病痛折磨好多年了，辛辛苦苦挨到了今日，可是我撑不下去了，真的好难",
    "like_counts": 0,
    "liked": false,
    "recordTime": "2023-05-21 晚上 11:55 星期日"
  },
  {
    "id": 4903984534391154,
    "created_at": "20分钟前",
    "source": "来自上海",
    "user": {
      "id": 3837195624,
      "screen_name": "何必之Code",
      "profile_image_url": "https://tvax1.sinaimg.cn/crop.0.0.640.640.180/e4b6f568ly8gdi6y2hqeyj20hs0hsq3d.jpg?KID=imgbed,tva&Expires=1684696540&ssig=Xzd%2BCWISe%2F",
      "verified": false,
      "verified_type": -1,
      "followers_count": "221",
      "followers_count_str": "221",
      "friends_count": 318,
      "mbtype": 0,
      "svip": 0,
      "profile_url": "https://m.weibo.cn/u/3837195624?",
      "remark": "",
      "following": false,
      "follow_me": false
    },
    "text": "李医生 我阳了 第一次阳 毫无征兆的 这一天总会来<span class=\"url-icon\"><img alt=[可爱] src=\"https://h5.sinaimg.cn/m/emoticon/icon/default/d_keai-9aae643ce8.png\" style=\"width:1em; height:1em;\" /></span>",
    "like_counts": 0,
    "liked": false,
    "recordTime": "2023-05-21 晚上 11:55 星期日"
  },
  {
    "id": 4903982840152562,
    "created_at": "27分钟前",
    "source": "来自浙江",
    "user": {
      "id": 1909909395,
      "screen_name": "不肉12345678",
      "profile_image_url": "https://tvax3.sinaimg.cn/crop.0.0.828.828.180/71d6e793ly8gryf2pc44qj20n00n0q4g.jpg?KID=imgbed,tva&Expires=1684696540&ssig=w2gtx%2FGwXN",
      "verified": false,
      "verified_type": -1,
      "followers_count": "36",
      "followers_count_str": "36",
      "friends_count": 338,
      "mbtype": 0,
      "svip": 0,
      "profile_url": "https://m.weibo.cn/u/1909909395?",
      "remark": "",
      "following": false,
      "follow_me": false
    },
    "text": "李医生，为什么幸福如履薄冰呢？为什么想幸福就那么难呢？",
    "like_counts": 0,
    "liked": false,
    "recordTime": "2023-05-21 晚上 11:48 星期日"
  },
  {
    "id": 4903981875466162,
    "created_at": "31分钟前",
    "source": "来自湖南",
    "user": {
      "id": 7329043424,
      "screen_name": "历史作业赶紧写",
      "profile_image_url": "https://tvax3.sinaimg.cn/crop.0.0.1023.1023.180/007ZZUZOly8gxy13xgdfrj30sg0sfdgx.jpg?KID=imgbed,tva&Expires=1684696540&ssig=ZcmunKVaiJ",
      "verified": false,
      "verified_type": -1,
      "followers_count": "1",
      "followers_count_str": "1",
      "friends_count": 91,
      "mbtype": 0,
      "svip": 0,
      "profile_url": "https://m.weibo.cn/u/7329043424?",
      "remark": "",
      "following": false,
      "follow_me": false
    },
    "text": "李医生，近来感觉我的灵魂进入一中趋于死水的境地了。我对外界的新鲜感和好奇都没有上个学期浓厚了。唉，这样的生活如此难过",
    "like_counts": 0,
    "liked": false,
    "recordTime": "2023-05-21 晚上 11:44 星期日"
  },
  {
    "id": 4903980741692266,
    "created_at": "35分钟前",
    "source": "来自甘肃",
    "user": {
      "id": 6719142196,
      "screen_name": "白日梦想家深藏blue",
      "profile_image_url": "https://tvax1.sinaimg.cn/crop.0.0.512.512.180/007kIPPely8hd8jxvxdsuj30e80e8t90.jpg?KID=imgbed,tva&Expires=1684696540&ssig=vYaC%2FGxgcM",
      "verified": false,
      "verified_type": -1,
      "followers_count": "273",
      "followers_count_str": "273",
      "friends_count": 244,
      "mbtype": 2,
      "svip": 0,
      "profile_url": "https://m.weibo.cn/u/6719142196?",
      "remark": "",
      "following": false,
      "follow_me": false
    },
    "text": "李医生晚安[发射爱心]",
    "like_counts": 0,
    "liked": false,
    "recordTime": "2023-05-21 晚上 11:40 星期日"
  },
  {
    "id": 4903980670914935,
    "created_at": "36分钟前",
    "source": "来自福建",
    "user": {
      "id": 5406713003,
      "screen_name": "Lin-Ultraman",
      "profile_image_url": "https://tvax1.sinaimg.cn/crop.0.0.1080.1080.180/005TU12rly8guko0locfjj60u00u0n0902.jpg?KID=imgbed,tva&Expires=1684696540&ssig=z99qNVvd3C",
      "verified": false,
      "verified_type": -1,
      "followers_count": "436",
      "followers_count_str": "436",
      "friends_count": 242,
      "mbtype": 2,
      "svip": 0,
      "profile_url": "https://m.weibo.cn/u/5406713003?",
      "remark": "",
      "following": false,
      "follow_me": false
    },
    "text": "回复<a href='https://m.weibo.cn/n/低血糖蛋白'>@低血糖蛋白</a>:上周去已经拍完毕业照了",
    "reply_id": 4903975567230831,
    "reply_text": "<a href='https://m.weibo.cn/n/Lin-Ultraman'>@Lin-Ultraman</a> 在大学生放假前去一次学校吧，今天看到他们拍毕业照的视频意识到大家好像要放暑假了",
    "like_counts": 0,
    "liked": false,
    "recordTime": "2023-05-21 晚上 11:39 星期日"
  },
  {
    "id": 4903980578638694,
    "created_at": "36分钟前",
    "source": "来自江苏",
    "user": {
      "id": 7800980832,
      "screen_name": "琳姐姐_09",
      "profile_image_url": "https://tvax2.sinaimg.cn/crop.0.0.1080.1080.180/008vW7tuly8ha8o1n3p3rj30u00u0q53.jpg?KID=imgbed,tva&Expires=1684696540&ssig=bH1JTH0zdF",
      "verified": false,
      "verified_type": -1,
      "followers_count": "0",
      "followers_count_str": "0",
      "friends_count": 25,
      "mbtype": 0,
      "svip": 0,
      "profile_url": "https://m.weibo.cn/u/7800980832?",
      "remark": "",
      "following": false,
      "follow_me": false
    },
    "text": "李医生，我今晚又哭了，还在坚持，但快到极限了……",
    "like_counts": 0,
    "liked": false,
    "recordTime": "2023-05-21 晚上 11:39 星期日"
  }
]
