[
  {
    "id": 5034809837750306,
    "created_at": "刚刚",
    "source": "来自江苏",
    "user": {
      "id": 6209225376,
      "screen_name": "A周壮",
      "profile_image_url": "https://tvax1.sinaimg.cn/crop.0.0.512.512.180/006Mdhaoly8g0d4d6oc07j30e80e83z2.jpg?KID=imgbed,tva&Expires=1715886478&ssig=xuJiMUI5yc",
      "verified": false,
      "verified_type": -1,
      "followers_count": "2",
      "followers_count_str": "2",
      "friends_count": 224,
      "mbtype": 0,
      "svip": 0,
      "profile_url": "https://m.weibo.cn/u/6209225376?",
      "remark": "",
      "following": false,
      "follow_me": false
    },
    "text": "老李，庆余年2开播了，一定在天堂里的看哦<span class=\"url-icon\"><img alt=[心] src=\"https://h5.sinaimg.cn/m/emoticon/icon/others/l_xin-43af9086c0.png\" style=\"width:1em; height:1em;\" /></span>",
    "like_counts": 0,
    "liked": false,
    "recordTime": "2024-05-17 凌晨 12:07 星期五"
  },
  {
    "id": 5034809829887345,
    "created_at": "刚刚",
    "source": "来自山西",
    "user": {
      "id": 5046425098,
      "screen_name": "aYaxHx_9",
      "profile_image_url": "https://tvax4.sinaimg.cn/crop.0.0.512.512.180/005vwhHcly8hpobdknoi1j30e80e8gm0.jpg?KID=imgbed,tva&Expires=1715886478&ssig=r6%2Bw%2B4yQ0m",
      "verified": false,
      "verified_type": -1,
      "followers_count": "77",
      "followers_count_str": "77",
      "friends_count": 270,
      "mbtype": 2,
      "svip": 1,
      "profile_url": "https://m.weibo.cn/u/5046425098?",
      "remark": "",
      "following": false,
      "follow_me": false
    },
    "text": "回复<a href='https://m.weibo.cn/n/aYaxHx_9'>@aYaxHx_9</a>:24年我也去了武汉 武汉也很好玩<span class=\"url-icon\"><img alt=[泪] src=\"https://h5.sinaimg.cn/m/emoticon/icon/default/d_lei-4cdf6ee412.png\" style=\"width:1em; height:1em;\" /></span>",
    "reply_id": 5034809656609640,
    "reply_text": "李医生 庆余年2开播了",
    "like_counts": 0,
    "liked": false,
    "recordTime": "2024-05-17 凌晨 12:07 星期五"
  },
  {
    "id": 5034809796069836,
    "created_at": "刚刚",
    "source": "来自广东",
    "user": {
      "id": 2036108411,
      "screen_name": "SSSKrystal",
      "profile_image_url": "https://tvax1.sinaimg.cn/crop.0.0.828.828.180/795c8c7bly8gszgdqjwv2j20n00n0jth.jpg?KID=imgbed,tva&Expires=1715886478&ssig=f%2F%2FG4KTFFf",
      "verified": false,
      "verified_type": 220,
      "followers_count": "941",
      "followers_count_str": "941",
      "friends_count": 1163,
      "mbtype": 0,
      "svip": 0,
      "profile_url": "https://m.weibo.cn/u/2036108411?",
      "remark": "",
      "following": false,
      "follow_me": false
    },
    "text": "开播了哥，一切都好",
    "like_counts": 0,
    "liked": false,
    "recordTime": "2024-05-17 凌晨 12:07 星期五"
  },
  {
    "id": 5034809749670252,
    "created_at": "刚刚",
    "source": "来自江苏",
    "user": {
      "id": 7765749612,
      "screen_name": "jdjaidbidjxnak",
      "profile_image_url": "https://tvax1.sinaimg.cn/crop.0.0.1080.1080.180/008tyie0ly8hovcml2xx5j30u00u075r.jpg?KID=imgbed,tva&Expires=1715886478&ssig=BcXqIlwKMh",
      "verified": false,
      "verified_type": -1,
      "followers_count": "3",
      "followers_count_str": "3",
      "friends_count": 329,
      "mbtype": 0,
      "svip": 0,
      "profile_url": "https://m.weibo.cn/u/7765749612?",
      "remark": "",
      "following": false,
      "follow_me": false
    },
    "text": "李医生，庆余年2开播啦",
    "like_counts": 0,
    "liked": false,
    "recordTime": "2024-05-17 凌晨 12:07 星期五"
  },
  {
    "id": 5034809678889500,
    "created_at": "刚刚",
    "source": "来自江苏",
    "user": {
      "id": 2609855627,
      "screen_name": "尔歇米",
      "profile_image_url": "https://tvax1.sinaimg.cn/crop.0.0.1080.1080.180/9b8f3c8bly8gyrevmr5hoj20u00u0q53.jpg?KID=imgbed,tva&Expires=1715886478&ssig=h0ckfhJxl9",
      "verified": false,
      "verified_type": -1,
      "followers_count": "48",
      "followers_count_str": "48",
      "friends_count": 190,
      "mbtype": 0,
      "svip": 0,
      "profile_url": "https://m.weibo.cn/u/2609855627?",
      "remark": "",
      "following": false,
      "follow_me": false
    },
    "text": "开播啦",
    "like_counts": 2,
    "liked": false,
    "recordTime": "2024-05-17 凌晨 12:07 星期五"
  },
  {
    "id": 5034809656609640,
    "created_at": "刚刚",
    "source": "来自山西",
    "user": {
      "id": 5046425098,
      "screen_name": "aYaxHx_9",
      "profile_image_url": "https://tvax4.sinaimg.cn/crop.0.0.512.512.180/005vwhHcly8hpobdknoi1j30e80e8gm0.jpg?KID=imgbed,tva&Expires=1715886478&ssig=r6%2Bw%2B4yQ0m",
      "verified": false,
      "verified_type": -1,
      "followers_count": "77",
      "followers_count_str": "77",
      "friends_count": 270,
      "mbtype": 2,
      "svip": 1,
      "profile_url": "https://m.weibo.cn/u/5046425098?",
      "remark": "",
      "following": false,
      "follow_me": false
    },
    "text": "李医生 庆余年2开播了",
    "like_counts": 1,
    "liked": false,
    "recordTime": "2024-05-17 凌晨 12:07 星期五"
  },
  {
    "id": 5034809596316990,
    "created_at": "1分钟前",
    "source": "来自浙江",
    "user": {
      "id": 1780748497,
      "screen_name": "vicky-秦",
      "profile_image_url": "https://tvax1.sinaimg.cn/crop.0.0.1080.1080.180/6a2410d1ly8ho88umaqdxj20u00u10vh.jpg?KID=imgbed,tva&Expires=1715886478&ssig=ch4kQpNV39",
      "verified": false,
      "verified_type": -1,
      "followers_count": "559",
      "followers_count_str": "559",
      "friends_count": 97,
      "mbtype": 2,
      "svip": 0,
      "profile_url": "https://m.weibo.cn/u/1780748497?",
      "remark": "",
      "following": false,
      "follow_me": false
    },
    "text": "庆余年2，5年后开播了。可惜你再也看不到了<span class=\"url-icon\"><img alt=[泪] src=\"https://h5.sinaimg.cn/m/emoticon/icon/default/d_lei-4cdf6ee412.png\" style=\"width:1em; height:1em;\" /></span>",
    "like_counts": 2,
    "liked": false,
    "recordTime": "2024-05-17 凌晨 12:06 星期五"
  },
  {
    "id": 5034809550442776,
    "created_at": "1分钟前",
    "source": "来自上海",
    "user": {
      "id": 6878054678,
      "screen_name": "哑劇23543",
      "profile_image_url": "https://tvax4.sinaimg.cn/crop.0.0.1080.1080.180/007vtCdMly8gjjckz2di1j30u00u0dhk.jpg?KID=imgbed,tva&Expires=1715886478&ssig=paYgRlDV7O",
      "verified": false,
      "verified_type": -1,
      "followers_count": "3",
      "followers_count_str": "3",
      "friends_count": 172,
      "mbtype": 0,
      "svip": 0,
      "profile_url": "https://m.weibo.cn/u/6878054678?",
      "remark": "",
      "following": false,
      "follow_me": false
    },
    "text": "李医生~庆余年开播了哦！",
    "like_counts": 0,
    "liked": false,
    "recordTime": "2024-05-17 凌晨 12:06 星期五"
  },
  {
    "id": 5034809508236709,
    "created_at": "1分钟前",
    "source": "来自广东",
    "user": {
      "id": 2281895785,
      "screen_name": "你依_",
      "profile_image_url": "https://tvax4.sinaimg.cn/crop.0.0.179.179.180/8802f769ly8gastx7fvevj204z04za9x.jpg?KID=imgbed,tva&Expires=1715886478&ssig=kx9j2YlcB1",
      "verified": false,
      "verified_type": -1,
      "followers_count": "102",
      "followers_count_str": "102",
      "friends_count": 932,
      "mbtype": 12,
      "svip": 0,
      "profile_url": "https://m.weibo.cn/u/2281895785?",
      "remark": "",
      "following": false,
      "follow_me": false
    },
    "text": "庆余年2开播啦～我们已经度过了疫情，你若还在多好。",
    "like_counts": 0,
    "liked": false,
    "recordTime": "2024-05-17 凌晨 12:06 星期五"
  },
  {
    "id": 5034809480446640,
    "created_at": "1分钟前",
    "source": "来自江苏",
    "user": {
      "id": 5767085468,
      "screen_name": "飞翔的小熊8",
      "profile_image_url": "https://tva3.sinaimg.cn/crop.0.0.168.168.180/006ii6nyjw8ey7jfux84rj304o04ot8k.jpg?KID=imgbed,tva&Expires=1715886478&ssig=RYRkLeYFRH",
      "verified": false,
      "verified_type": -1,
      "followers_count": "26",
      "followers_count_str": "26",
      "friends_count": 671,
      "mbtype": 0,
      "svip": 0,
      "profile_url": "https://m.weibo.cn/u/5767085468?",
      "remark": "",
      "following": false,
      "follow_me": false
    },
    "text": "李医生庆余年2开播了，特种过来告诉你",
    "like_counts": 0,
    "liked": false,
    "recordTime": "2024-05-17 凌晨 12:06 星期五"
  }
]
